fliq/__init__.py
fliq/_types.py
fliq/exceptions.py
fliq/query.py
fliq/tests/__init__.py
fliq/tests/fliq_test_utils.py
fliq/tests/timer.py
fliq/tests/mappers/__init__.py
fliq/tests/mappers/test_append.py
fliq/tests/mappers/test_append_many.py
fliq/tests/mappers/test_bottom.py
fliq/tests/mappers/test_distinct.py
fliq/tests/mappers/test_exclude.py
fliq/tests/mappers/test_flatten.py
fliq/tests/mappers/test_group_by.py
fliq/tests/mappers/test_interleave.py
fliq/tests/mappers/test_order_by.py
fliq/tests/mappers/test_pairwise.py
fliq/tests/mappers/test_prepend.py
fliq/tests/mappers/test_prepend_many.py
fliq/tests/mappers/test_reverse.py
fliq/tests/mappers/test_select.py
fliq/tests/mappers/test_shuffle.py
fliq/tests/mappers/test_skip.py
fliq/tests/mappers/test_slice.py
fliq/tests/mappers/test_slide.py
fliq/tests/mappers/test_take.py
fliq/tests/mappers/test_top.py
fliq/tests/mappers/test_where.py
fliq/tests/mappers/test_zip.py
fliq/tests/materializer/__init__.py
fliq/tests/materializer/test_to_dict.py
fliq/tests/materializer/test_to_list.py
fliq/tests/materializer/reducers/__init__.py
fliq/tests/materializer/reducers/test_aggregate.py
fliq/tests/materializer/reducers/test_all.py
fliq/tests/materializer/reducers/test_any.py
fliq/tests/materializer/reducers/test_contains.py
fliq/tests/materializer/reducers/test_count.py
fliq/tests/materializer/reducers/test_equals.py
fliq/tests/materializer/reducers/test_first.py
fliq/tests/materializer/reducers/test_max.py
fliq/tests/materializer/reducers/test_min.py
fliq/tests/materializer/reducers/test_most_common.py
fliq/tests/materializer/reducers/test_sample.py
fliq/tests/materializer/reducers/test_single.py
fliq/tests/materializer/reducers/test_sum.py
fliq/tests/materializer/reducers/special_reducers/__init__.py
fliq/tests/materializer/reducers/special_reducers/test_eq.py
fliq/tests/materializer/reducers/special_reducers/test_in.py
fliq/tests/special/__init__.py
fliq/tests/special/test_partition.py
fliq/tests/special/test_peek.py
fliq-1.12.0.dist-info/LICENSE
fliq-1.12.0.dist-info/METADATA
fliq-1.12.0.dist-info/WHEEL
fliq-1.12.0.dist-info/top_level.txt
fliq-1.12.0.dist-info/RECORD
