Metadata-Version: 2.1
Name: fliq
Version: 1.12.0
Summary: Fluent-based Lazily-evaluated Integrated Query for Python
Author-email: Ori Bar-ilan <python.oplog@gmail.com>
License: MIT License
Project-URL: Homepage, https://github.com/oribarilan/fliq
Keywords: fliq,lazy,fluent,lisp,linq
Classifier: License :: OSI Approved :: MIT License
Classifier: Programming Language :: Python
Classifier: Programming Language :: Python :: 3
Requires-Python: >=3.9
License-File: LICENSE
